xmlcoll/__about__.py
xmlcoll/__init__.py
xmlcoll/base.py
xmlcoll/coll.py
xmlcoll/xsd_pub/catalog
xmlcoll/xsd_pub/xmlcoll.xsd
xmlcoll/xsd_pub/xmlcoll_types.xsd
xmlcoll-1.8.3.dist-info/LICENSE
xmlcoll-1.8.3.dist-info/METADATA
xmlcoll-1.8.3.dist-info/WHEEL
xmlcoll-1.8.3.dist-info/top_level.txt
xmlcoll-1.8.3.dist-info/RECORD
