Metadata-Version: 2.1
Name: xmlcoll
Version: 1.8.3
Summary: Python project to work with xml data of a collection of items.
Home-page: https://github.com/mbradle/xmlcoll
Author: Clemson University
Author-email: mbradle@clemson.edu
License: GPLv3+
Project-URL: Bug Reports, https://github.com/mbradle/xmlcoll/issues
Project-URL: Source, https://github.com/mbradle/xmlcoll/
Keywords: data xml database collection
Classifier: Development Status :: 5 - Production/Stable
Classifier: Intended Audience :: Information Technology
Classifier: Intended Audience :: End Users/Desktop
Classifier: Topic :: Database
Classifier: Topic :: Text Processing :: Markup :: XML
Classifier: License :: OSI Approved :: GNU General Public License v3 or later (GPLv3+)
Classifier: Programming Language :: Python :: 3
License-File: LICENSE
Requires-Dist: lxml
Requires-Dist: pandas
Provides-Extra: dev
Requires-Dist: check-manifest; extra == "dev"
Provides-Extra: test
Requires-Dist: coverage; extra == "test"
